{
  "operation": "list-completed-jobs",
  "method": "GET",
  "path": "/w/{workspace}/jobs/completed/list",
  "summary": "List Completed Jobs",
  "request": {
    "workspace": "my-workspace",
    "per_page": 30,
    "page": 1
  },
  "response": [
    {
      "id": "d99723d1-3a55-4a0c-8f29-e4f7f6b7d1b2",
      "workspace_id": "my-workspace",
      "type": "RunnerJob",
      "status": "success",
      "created_at": "2026-05-03T10:00:00Z",
      "started_at": "2026-05-03T10:00:01Z",
      "duration_ms": 1234,
      "script_path": "u/user/hello_world",
      "args": {
        "name": "World"
      }
    }
  ]
}